[
    {
        "name": "Dark Ruins",
        "color": "#FFFFFF",
        "children": [
            
            {
                "name": "Dark Ruins",
                "map_locations": [
                    {
                        "map": "Dark_Ruins",
                        "x": 0,
                        "y": 0
                    },
                    {
                        "map": "Mysterious_Age",
                        "x": 175,
                        "y": 195
                    }
                ],
                "access_rules": 
                        [
                            "dr_key"
                        ],
                "sections": [
                    {
                        "name": "Kyle",
                        "chest_unopened_img": "images/icons/monkeyOn.png",
                        "chest_opened_img": "images/icons/monkeyOff.png",
                        "visibility_rules": 
                        [
                            ""
                        ],
                        "access_rules": 
                        [
                            "net, $CanHitOnce",
                            "net, flyer"

                        ],
                        "item_count": 1
                    },
                    {
                        "name": "Stan",
                        "chest_unopened_img": "images/icons/monkeyOn.png",
                        "chest_opened_img": "images/icons/monkeyOff.png",
                        "visibility_rules": 
                        [
                            ""
                        ],
                        "access_rules": 
                        [
                            "net"
                        ],
                        "item_count": 1
                    },
                    {
                        "name": "Kenny",
                        "chest_unopened_img": "images/icons/monkeyOn.png",
                        "chest_opened_img": "images/icons/monkeyOff.png",
                        "visibility_rules": 
                        [
                            ""
                        ],
                        "access_rules": 
                        [
                            "net"
                        ],
                        "item_count": 1
                    },
                    {
                        "name": "Cratman",
                        "chest_unopened_img": "images/icons/monkeyOn.png",
                        "chest_opened_img": "images/icons/monkeyOff.png",
                        "visibility_rules": 
                        [
                            ""
                        ],
                        "access_rules": 
                        [
                            "net"
                        ],
                        "item_count": 1
                    },
                    {
                        "name": "Mooshy",
                        "chest_unopened_img": "images/icons/monkeyOn.png",
                        "chest_opened_img": "images/icons/monkeyOff.png",
                        "visibility_rules": 
                        [
                            ""
                        ],
                        "access_rules": 
                        [
                            "net, hoop",
                            "net, op_no_ij",
                            "net, op_et"
                        ],
                        "item_count": 1
                    },
                    {
                        "name": "Nuzzy",
                        "chest_unopened_img": "images/icons/monkeyOn.png",
                        "chest_opened_img": "images/icons/monkeyOff.png",
                        "visibility_rules": 
                        [
                            ""
                        ],
                        "access_rules": 
                        [
                            "net, sling",
                            "net, punch",
                            "net, hoop",
                            "net, op_no_ij",
                            "net, op_et"
                        ],
                        "item_count": 1
                    },
                    {
                        "name": "Mav",
                        "chest_unopened_img": "images/icons/monkeyOn.png",
                        "chest_opened_img": "images/icons/monkeyOff.png",
                        "visibility_rules": 
                        [
                            ""
                        ],
                        "access_rules": 
                        [
                            "net"
                        ],
                        "item_count": 1
                    },
                    {
                        "name": "Papou",
                        "chest_unopened_img": "images/icons/monkeyOn.png",
                        "chest_opened_img": "images/icons/monkeyOff.png",
                        "visibility_rules": 
                        [
                            ""
                        ],
                        "access_rules": 
                        [
                            "net"
                        ],
                        "item_count": 1
                    },
                    {
                        "name": "Trance",
                        "chest_unopened_img": "images/icons/monkeyOn.png",
                        "chest_opened_img": "images/icons/monkeyOff.png",
                        "visibility_rules": 
                        [
                            ""
                        ],
                        "access_rules": 
                        [
                            "net"
                        ],
                        "item_count": 1
                    },
                    {
                        "name": "Bernt",
                        "chest_unopened_img": "images/icons/monkeyOn.png",
                        "chest_opened_img": "images/icons/monkeyOff.png",
                        "visibility_rules": 
                        [
                            ""
                        ],
                        "access_rules": 
                        [
                            "net, sling",
                            "net, punch, op_no_ij",
                            "net, punch, op_et"
                        ],
                        "item_count": 1
                    },
                    {
                        "name": "Runt",
                        "chest_unopened_img": "images/icons/monkeyOn.png",
                        "chest_opened_img": "images/icons/monkeyOff.png",
                        "visibility_rules": 
                        [
                            ""
                        ],
                        "access_rules": 
                        [
                            "net, $CanSwim, sling, $CanHitOnce",
                            "net, $CanSwim, sling, flyer",
                            "net, $CanSwim, hoop, $CanHitOnce",
                            "net, $CanSwim, hoop, flyer",
                            "net, $CanSwim, $CanHitOnce, op_no_ij",
                            "net, sling, op_no_ij",
                            "net, hoop, op_no_ij",
                            "net, $CanSwim, $CanHitOnce, op_et",
                            "net, sling, op_et",
                            "net, hoop, op_et"
                        ],
                        "item_count": 1
                    },
                    {
                        "name": "Hoolah",
                        "chest_unopened_img": "images/icons/monkeyOn.png",
                        "chest_opened_img": "images/icons/monkeyOff.png",
                        "visibility_rules": 
                        [
                            ""
                        ],
                        "access_rules": 
                        [
                            "net, $CanHitMultiple"
                        ],
                        "item_count": 1
                    },
                    {
                        "name": "Chino",
                        "chest_unopened_img": "images/icons/monkeyOn.png",
                        "chest_opened_img": "images/icons/monkeyOff.png",
                        "visibility_rules": 
                        [
                            ""
                        ],
                        "access_rules": 
                        [
                            "net, $CanSwim, sling, $CanHitOnce",
                            "net, $CanSwim, sling, flyer",
                            "net, $CanSwim, hoop, $CanHitOnce",
                            "net, $CanSwim, hoop, flyer",
                            "net, $CanSwim, $CanHitOnce, op_no_ij",
                            "net, sling, op_no_ij",
                            "net, hoop, op_no_ij",
                            "net, $CanSwim, $CanHitOnce, op_et",
                            "net, sling, op_et",
                            "net, hoop, op_et"
                        ],
                        "item_count": 1
                    },
                    {
                        "name": "Outside",
                        "chest_unopened_img": "images/icons/coinOn.png",
                        "chest_opened_img": "images/icons/coinOff.png",
                        "visibility_rules": 
                        [
                            "shuffleCoins"
                        ],
                        "access_rules": 
                        [
                            ""
                        ],
                        "item_count": 1
                    },
                    {
                        "name": "Fan Basement",
                        "chest_unopened_img": "images/icons/coinOn.png",
                        "chest_opened_img": "images/icons/coinOff.png",
                        "visibility_rules": 
                        [
                            "shuffleCoins"
                        ],
                        "access_rules": 
                        [
                            ""
                        ],
                        "item_count": 1
                    },
                    {
                        "name": "Obelisk Inside",
                        "chest_unopened_img": "images/icons/coinOn.png",
                        "chest_opened_img": "images/icons/coinOff.png",
                        "visibility_rules": 
                        [
                            "shuffleCoins"
                        ],
                        "access_rules": 
                        [
                            "car",
                            "punch",
                            "hoop, flyer, op_no_ij",
                            "sling, op_et",
                            "hoop, flyer, op_et"
                        ],
                        "item_count": 1
                    },
                    {
                        "name": "Water Basement",
                        "chest_unopened_img": "images/icons/coinOn.png",
                        "chest_opened_img": "images/icons/coinOff.png",
                        "visibility_rules": 
                        [
                            "shuffleCoins"
                        ],
                        "access_rules": 
                        [
                            "$CanDive, $CanHitOnce",
                            "$CanDive, flyer"
                        ],
                        "item_count": 1
                    },
                    {
                        "name": "Time Trial",
                        "visibility_rules": 
                        [
                            "shuffleTT"
                        ],
                        "access_rules": 
                        [
                            "net, hoop",
                            "net, flyer",
                            "net, op_no_ij",
                            "net, op_et"
                        ],
                        "item_count": 1
                    }
                ]
            }
        ]
    }
]
