[
    {
        "name": "Snowy Mammoth",
        "color": "#FFFFFF",
        "children": [
            {
                "name": "Snowy Mammoth",
                "map_locations": [
                    {
                        "map": "Snowy_Mammoth",
                        "x": 0,
                        "y": 0
                    },
                    {
                        "map": "New_Freezeland",
                        "x": 45,
                        "y": 145
                    }
                ],
                "access_rules": 
                        [
                            "sm_key"
                        ],
                "sections": [
                    {
                        "name": "Popcicle",
                        "chest_unopened_img": "images/icons/monkeyOn.png",
                        "chest_opened_img": "images/icons/monkeyOff.png",
                        "visibility_rules": 
                        [
                            ""
                        ],
                        "access_rules": 
                        [
                            "net"
                        ],
                        "item_count": 1
                    },
                    {
                        "name": "Iced",
                        "chest_unopened_img": "images/icons/monkeyOn.png",
                        "chest_opened_img": "images/icons/monkeyOff.png",
                        "visibility_rules": 
                        [
                            ""
                        ],
                        "access_rules": 
                        [
                            "net, $CanHitOnce"
                        ],
                        "item_count": 1
                    },
                    {
                        "name": "Rickets",
                        "chest_unopened_img": "images/icons/monkeyOn.png",
                        "chest_opened_img": "images/icons/monkeyOff.png",
                        "visibility_rules": 
                        [
                            ""
                        ],
                        "access_rules": 
                        [
                            "net, sling",
                            "net, punch, op_no_ij",
                            "net, club, flyer, op_no_ij",
                            "net, punch, op_et",
                            "net, club, flyer, op_et"

                        ],
                        "item_count": 1
                    },
                    {
                        "name": "Skeens",
                        "chest_unopened_img": "images/icons/monkeyOn.png",
                        "chest_opened_img": "images/icons/monkeyOff.png",
                        "visibility_rules": 
                        [
                            ""
                        ],
                        "access_rules": 
                        [
                            "net, $CanHitMultiple",
                            "net, flyer",
                            "net, op_no_ij",
                            "net, op_et"
                        ],
                        "item_count": 1
                    },
                    {
                        "name": "Denggoy",
                        "chest_unopened_img": "images/icons/monkeyOn.png",
                        "chest_opened_img": "images/icons/monkeyOff.png",
                        "visibility_rules": 
                        [
                            ""
                        ],
                        "access_rules": 
                        [
                            "net, $CanHitMultiple",
                            "net, flyer",
                            "net, op_no_ij",
                            "net, op_et"
                        ],
                        "item_count": 1
                    },
                    {
                        "name": "Chilly",
                        "chest_unopened_img": "images/icons/monkeyOn.png",
                        "chest_opened_img": "images/icons/monkeyOff.png",
                        "visibility_rules": 
                        [
                            ""
                        ],
                        "access_rules": 
                        [
                            "net, $CanHitMultiple",
                            "net, flyer",
                            "net, op_no_ij",
                            "net, op_et"
                        ],
                        "item_count": 1
                    },
                    {
                        "name": "Main",
                        "chest_unopened_img": "images/icons/coinOn.png",
                        "chest_opened_img": "images/icons/coinOff.png",
                        "visibility_rules": 
                        [
                            "shuffleCoins"
                        ],
                        "access_rules": 
                        [
                            ""
                        ],
                        "item_count": 1
                    },
                    {
                        "name": "Time Trial",
                        "visibility_rules": 
                        [
                            "shuffleTT"
                        ],
                        "access_rules": 
                        [
                            "net, hoop, $CanHitMultiple",
                            "net, flyer",
                            "net, op_no_ij",
                            "net, op_et"
                        ],
                        "item_count": 1
                    }
                ]
            }
        ]
    }
]